snowflake_client/__init__.py
snowflake_client/py.typed
snowflake_client/_core/__init__.py
snowflake_client/_core/clients.py
snowflake_client/_core/connection.py
snowflake_client/_core/cursor.py
snowflake_client/_core/query.py
snowflake_client/_factory/__init__.py
snowflake_client/_factory/connection.py
snowflake_client/_factory/cursor.py
snowflake_client/_factory/schema/__init__.py
snowflake_client/_factory/schema/_methods.py
snowflake_client/_factory/table/__init__.py
snowflake_client/_factory/table/_assert.py
snowflake_client/_factory/table/_encode.py
snowflake_client/_factory/table/_methods.py
snowflake_client/_factory/table/_new.py
snowflake_client-4.0.0.dist-info/WHEEL
snowflake_client-4.0.0.dist-info/METADATA
snowflake_client-4.0.0.dist-info/RECORD
