Metadata-Version: 2.4
Name: snowflake_client
Version: 4.0.0
Summary: Snowflake client SDK
Author-email: Product Team <development@fluidattacks.com>
Requires-Python: >=3.11
Classifier: License :: OSI Approved :: MIT License
Requires-Dist: boto3 >=1.28.57, <2.0.0
Requires-Dist: boto3-stubs >=1.34.160, <2.0.0
Requires-Dist: Deprecated >=1.2.12, <2.0.0
Requires-Dist: fa-purity >=2.0.0, <3.0.0
Requires-Dist: redshift-client >=9.0.0, <10.0.0
Requires-Dist: snowflake-connector-python >=3.12.1, <4.0.0
Requires-Dist: types-Deprecated >=1.2.1, <2.0.0
